{
    "version": "1.0.0",
    "discord": {
        "clientId": "12334567890123456789",
        "smallImageText": "WesterosCraft",
        "smallImageKey": "seal-circle"
    },
    "servers": [
        {
            "id": "VOID",
            "name": "VOID",
            "description": "VOID Server",
            "icon": "https://www.svgrepo.com/show/358843/damage-void.svg",
            "version": "1.0.0",
            "address": "localhost:25565",
            "minecraftVersion": "1.20.1",
            "discord": {
                "shortId": "Example",
                "largeImageText": "WesterosCraft Example Server",
                "largeImageKey": "server-example"
            },
            "mainServer": true,
            "autoconnect": true,
            "modules": [
                {
                    "id": "net.fabricmc:fabric-loader:0.18.1",
                    "name": "Fabric (fabric-loader)",
                    "type": "Fabric",
                    "artifact": {
                        "size": 1196222,
                        "MD5": "a43d5a142246801343b6cedef1c102c4",
                        "url": "https://newt-com.github.io/void-distribution/mods/fabric-api-0.92.6+1.20.1.jar"
                    }
                }
            ]
        }
    ]
}